{
  "project_info": {
    "project_number": "547368357690",
    "project_id": "luor-5aca7",
    "storage_bucket": "luor-5aca7.appspot.com"
  },
  "client": [
    {
      "client_info": {
        "mobilesdk_app_id": "1:547368357690:android:e443683741d23424788a03",
        "android_client_info": {
          "package_name": "com.fatec.petguide"
        }
      },
      "oauth_client": [],
      "api_key": [
        {
          "current_key": "AIzaSyDveCVDKIIDpHaYK2QeC8z1YOjFF2kb3cA"
        }
      ],
      "services": {
        "appinvite_service": {
          "other_platform_oauth_client": []
        }
      }
    }
  ],
  "configuration_version": "1"
}